setup.py
examples/interactive.py
examples/quordle.py
examples/simple.py
examples/solutions.py
pywordle/__init__.py
pywordle/game.py
pywordle/wordle.py
pywordle/words.py
pywordle2-0.0.0.7.dist-info/METADATA
pywordle2-0.0.0.7.dist-info/WHEEL
pywordle2-0.0.0.7.dist-info/licenses/LICENSE
pywordle2-0.0.0.7.dist-info/RECORD
