Metadata-Version: 2.1
Name: pywordle2
Version: 0.0.0.7
Summary: Game engine for the game Wordle
Project-URL: Homepage, https://github.com/agale123/py-wordle
Project-URL: Bug Tracker, https://github.com/agale123/py-wordle/issues
Author-email: Alison Gale <agale123.dev@gmail.com>
License-File: LICENSE
Classifier: License :: OSI Approved :: MIT License
Classifier: Operating System :: OS Independent
Classifier: Programming Language :: Python :: 3
Requires-Python: >=3.7
Requires-Dist: enum
Requires-Dist: termcolor
